examples/__init__.py
multivenv_test_package/__init__.py
tests/__init__.py
tests/test_placeholder.py
multivenv_test_package-1.1.0.dist-info/LICENSE.md
multivenv_test_package-1.1.0.dist-info/METADATA
multivenv_test_package-1.1.0.dist-info/WHEEL
multivenv_test_package-1.1.0.dist-info/top_level.txt
multivenv_test_package-1.1.0.dist-info/RECORD
