Metadata-Version: 2.1
Name: multivenv-test-package
Version: 1.1.0
Summary: A package to use as test data for testing the multivenv package
Home-page: https://github.com/nickderobertis/multivenv-test-package
Author: Nick DeRobertis
Author-email: derobertis.nick@gmail.com
License: MIT
Project-URL: Code, https://github.com/nickderobertis/multivenv-test-package
Project-URL: Documentation, https://nickderobertis.github.io/multivenv-test-package
Classifier: Development Status :: 3 - Alpha
Classifier: Intended Audience :: Developers
Classifier: Programming Language :: Python :: 3.6
Classifier: Programming Language :: Python :: 3.7
License-File: LICENSE.md
Requires-Dist: pywin32 (>=1.0) ; platform_system == "Windows"
